bob/__init__.py
bob/fusion/__init__.py
bob/fusion/base/__init__.py
bob/fusion/base/algorithm/AND.py
bob/fusion/base/algorithm/Algorithm.py
bob/fusion/base/algorithm/AlgorithmBob.py
bob/fusion/base/algorithm/Empty.py
bob/fusion/base/algorithm/GMM.py
bob/fusion/base/algorithm/Weighted_Sum.py
bob/fusion/base/algorithm/__init__.py
bob/fusion/base/config/__init__.py
bob/fusion/base/config/algorithm/__init__.py
bob/fusion/base/config/algorithm/gmm.py
bob/fusion/base/config/algorithm/llr_skl.py
bob/fusion/base/config/algorithm/mean.py
bob/fusion/base/config/algorithm/plr_2.py
bob/fusion/base/config/algorithm/plr_3.py
bob/fusion/base/preprocessor/Tanh.py
bob/fusion/base/preprocessor/ZNorm.py
bob/fusion/base/preprocessor/__init__.py
bob/fusion/base/script/__init__.py
bob/fusion/base/script/boundary.py
bob/fusion/base/script/fuse.py
bob/fusion/base/script/fusion.py
bob/fusion/base/script/resource.py
bob/fusion/base/tools/__init__.py
bob/fusion/base/tools/common.py
bob/fusion/base/tools/plotting.py
bob.fusion.base-0.1.6.dist-info/COPYING
bob.fusion.base-0.1.6.dist-info/METADATA
bob.fusion.base-0.1.6.dist-info/WHEEL
bob.fusion.base-0.1.6.dist-info/entry_points.txt
bob.fusion.base-0.1.6.dist-info/top_level.txt
bob.fusion.base-0.1.6.dist-info/RECORD
