Metadata-Version: 2.1
Name: bob.fusion.base
Version: 0.1.6
Summary: Score fusion in biometric and pad experiments
Author-email: Amir Mohammadi <amir.mohammadi@idiap.ch>
License: GPLv3 License
Project-URL: documentation, https://www.idiap.ch/software/bob/docs/bob/bob.fusion.base/v0.1.6/sphinx/
Project-URL: homepage, https://pypi.org/project/bob.fusion.base/
Project-URL: repository, https://gitlab.idiap.ch/bob/bob.fusion.base
Project-URL: changelog, https://gitlab.idiap.ch/bob/bob.fusion.base/-/releases
Keywords: bob,score fusion,evaluation,biometric
Classifier: Framework :: Bob
Classifier: Development Status :: 3 - Alpha
Classifier: Intended Audience :: Developers
Classifier: License :: OSI Approved :: GNU General Public License v3 (GPLv3)
Classifier: Natural Language :: English
Classifier: Programming Language :: Python
Classifier: Topic :: Scientific/Engineering :: Artificial Intelligence
Requires-Python: >=3.9
License-File: COPYING
Requires-Dist: bob ==12.1.1
Requires-Dist: bob.measure ==6.1.1
Requires-Dist: bob.learn.em ==3.3.1
Requires-Dist: bob.bio.base ==8.1.1
Requires-Dist: bob.pad.base ==6.0.1
Requires-Dist: clapper ~=1.0
Requires-Dist: matplotlib ~=3.8
Requires-Dist: numpy ~=1.26
Requires-Dist: scikit-learn ~=1.4
Provides-Extra: doc
Requires-Dist: sphinx ; extra == 'doc'
Requires-Dist: sphinx-rtd-theme ; extra == 'doc'
Requires-Dist: sphinx-autodoc-typehints ; extra == 'doc'
Requires-Dist: auto-intersphinx ; extra == 'doc'
Requires-Dist: sphinxcontrib-programoutput ; extra == 'doc'
Provides-Extra: qa
Requires-Dist: pre-commit ; extra == 'qa'
Provides-Extra: test
Requires-Dist: pytest ; extra == 'test'
Requires-Dist: pytest-cov ; extra == 'test'
Requires-Dist: coverage ; extra == 'test'
